nonebot_plugin_jmcomic/.gitignore
nonebot_plugin_jmcomic/__init__.py
nonebot_plugin_jmcomic/config.py
nonebot_plugin_jmcomic/LICENSE
nonebot_plugin_jmcomic/pyproject.toml
nonebot_plugin_jmcomic/README.md
nonebot_plugin_jmcomic/utils.py
nonebot_plugin_jmcomic-0.1.9.dist-info/LICENSE
nonebot_plugin_jmcomic-0.1.9.dist-info/METADATA
nonebot_plugin_jmcomic-0.1.9.dist-info/WHEEL
nonebot_plugin_jmcomic-0.1.9.dist-info/RECORD
