Metadata-Version: 2.3
Name: nonebot-plugin-jmcomic
Version: 0.1.9
Summary: 下载禁漫本子并发送
License: MIT
Author: zhulinyv
Author-email: zhulinyv2005@outlook.com
Requires-Python: >=3.9,<4.0
Classifier: License :: OSI Approved :: MIT License
Classifier: Programming Language :: Python :: 3
Classifier: Programming Language :: Python :: 3.9
Classifier: Programming Language :: Python :: 3.10
Classifier: Programming Language :: Python :: 3.11
Classifier: Programming Language :: Python :: 3.12
Classifier: Programming Language :: Python :: 3.13
Requires-Dist: img2pdf (>=0.6.0,<0.7.0)
Requires-Dist: jmcomic (>=2.5.32,<3.0.0)
Requires-Dist: nonebot-adapter-onebot (>=2.2.3,<3.0.0)
Requires-Dist: nonebot-plugin-localstore (>=0.7.4,<0.8.0)
Requires-Dist: nonebot2 (>=2.2.1,<3.0.0)
